{
  "applicableTo": ["mep_interior_office"],
  "description": "Master lookup table for Office (Interior) MEP proposals. Values are selected based on the project's total built-up area (sqft). MOEF, CRZ, and High Rise are NOT applicable for interior projects.",
  "areaSlabs": [10000, 20000, 50000],
  "rate": {
    "description": "Rate in Rs. per sqft (except for 10,000 sqft which is a fixed Lump Sum)",
    "MEP": {
      "unit": "Rs. / L.S or Rs./sqft",
      "values": {
        "10000": { "type": "lumpsum", "amount": 200000, "display": "Rs. 2,00,000 (LS)" },
        "20000": { "type": "per_sqft", "rate": 16.00, "display": "Rs.16 per sqft." },
        "50000": { "type": "per_sqft", "rate": 14.00, "display": "Rs.14 per sqft." }
      }
    },
    "MOEF": {
      "unit": "N/A",
      "values": {
        "10000": { "type": "na", "display": "-" },
        "20000": { "type": "na", "display": "-" },
        "50000": { "type": "na", "display": "-" }
      }
    },
    "CRZ": {
      "unit": "N/A",
      "values": {
        "10000": { "type": "na", "display": "-" },
        "20000": { "type": "na", "display": "-" },
        "50000": { "type": "na", "display": "-" }
      }
    },
    "HighRise": {
      "unit": "N/A",
      "values": {
        "10000": { "type": "na", "display": "-" },
        "20000": { "type": "na", "display": "-" },
        "50000": { "type": "na", "display": "-" }
      }
    },
    "totalRate": {
      "description": "Total rate — not applicable for interior office (only MEP rate applies)",
      "values": {
        "10000": { "type": "na", "display": "-" },
        "20000": { "type": "na", "display": "-" },
        "50000": { "type": "na", "display": "-" }
      }
    }
  },
  "completionYears": {
    "description": "Estimated project completion in years (fractional). 0.3 ≈ 4 months, 0.6 ≈ 7 months, 1 = 1 year.",
    "values": {
      "10000": 0.3,
      "20000": 0.6,
      "50000": 1
    }
  },
  "meetingSchedule": {
    "description": "Number of site meetings per phase based on area. RCC checks are not applicable for interior office projects.",
    "phases": {
      "rccUpToTypical": {
        "label": "RCC Slab Checking for MEP up to Typical Floor",
        "values": {
          "10000": "NA",
          "20000": "NA",
          "50000": "NA"
        }
      },
      "rccAfterTypical": {
        "label": "RCC Slab Checking after Typical Floor",
        "values": {
          "10000": "Not in our Scope",
          "20000": "Not in our Scope",
          "50000": "Not in our Scope"
        }
      },
      "installationCoordination": {
        "label": "Installation Site Co-ordination",
        "values": {
          "10000": 5,
          "20000": 10,
          "50000": 15
        }
      },
      "testingAndCommissioning": {
        "label": "Testing and Commissioning",
        "values": {
          "10000": 2,
          "20000": 2,
          "50000": 2
        }
      },
      "handover": {
        "label": "Handover",
        "values": {
          "10000": 1,
          "20000": 1,
          "50000": 1
        }
      }
    },
    "totals": {
      "values": {
        "10000": 8,
        "20000": 13,
        "50000": 18
      }
    },
    "averagePerYear": {
      "description": "Average meetings per year = Total / Completion Years",
      "values": {
        "10000": 27,
        "20000": 21.7,
        "50000": 18
      }
    }
  }
}
